streamware/__init__.py
streamware/analysis_exporter.py
streamware/animal_detector.py
streamware/async_llm.py
streamware/bytetrack.py
streamware/cli.py
streamware/concurrent_frame_processor.py
streamware/config.py
streamware/context_builder.py
streamware/core.py
streamware/detection_pipeline.py
streamware/diagnostics.py
streamware/dsl.py
streamware/dsl_streamer_process.py
streamware/dsl_timing_logger.py
streamware/dsl_visualizer.py
streamware/exceptions.py
streamware/fast_capture.py
streamware/frame_diff_dsl.py
streamware/frame_optimizer.py
streamware/handler.py
streamware/helpers.py
streamware/image_optimize.py
streamware/image_optimizer.py
streamware/intent.py
streamware/keyframe_extractor.py
streamware/llm_client.py
streamware/llm_motion_prompt.py
streamware/mime.py
streamware/motion_dsl.py
streamware/motion_tracker.py
streamware/object_tracker.py
streamware/object_tracker_bytetrack.py
streamware/parallel_processor.py
streamware/patterns.py
streamware/performance_manager.py
streamware/presets.py
streamware/quick_cli.py
streamware/ramdisk_capture.py
streamware/realtime_dsl_server.py
streamware/realtime_visualizer.py
streamware/response_filter.py
streamware/setup.py
streamware/setup_utils.py
streamware/smart_detector.py
streamware/svg_visualizer.py
streamware/timing_logger.py
streamware/tts.py
streamware/tts_worker_process.py
streamware/uri.py
streamware/webhook_utils.py
streamware/workflow.py
streamware/yolo_detector.py
streamware/components/__init__.py
streamware/components/automation.py
streamware/components/curllm.py
streamware/components/deploy.py
streamware/components/desktop.py
streamware/components/discord.py
streamware/components/email.py
streamware/components/file.py
streamware/components/http.py
streamware/components/kafka.py
streamware/components/live_narrator.py
streamware/components/live_narrator_extra.py
streamware/components/llm.py
streamware/components/media.py
streamware/components/motion_diff.py
streamware/components/network_scan.py
streamware-0.2.108.dist-info/licenses/LICENSE
streamware-0.2.108.dist-info/METADATA
streamware-0.2.108.dist-info/WHEEL
streamware-0.2.108.dist-info/entry_points.txt
streamware-0.2.108.dist-info/top_level.txt
streamware-0.2.108.dist-info/RECORD
