Metadata-Version: 2.4
Name: streamware
Version: 0.2.108
Summary: Modern Python stream processing framework inspired by Apache Camel
Home-page: https://github.com/softreck/streamware
Author: Softreck Team
Author-email: Softreck <info@softreck.com>
License-Expression: Apache-2.0
Project-URL: Homepage, https://github.com/stream-ware/streamware
Project-URL: Documentation, https://streamware.readthedocs.io
Project-URL: Repository, https://github.com/stream-ware/streamware
Project-URL: Bug Tracker, https://github.com/stream-ware/streamware/issues
Keywords: stream,processing,camel,workflow,pipeline,curllm,rtsp,kafka,rabbitmq
Classifier: Development Status :: 4 - Beta
Classifier: Intended Audience :: Developers
Classifier: Programming Language :: Python :: 3
Classifier: Programming Language :: Python :: 3.8
Classifier: Programming Language :: Python :: 3.9
Classifier: Programming Language :: Python :: 3.10
Classifier: Programming Language :: Python :: 3.11
Classifier: Programming Language :: Python :: 3.12
Classifier: Topic :: Software Development :: Libraries :: Python Modules
Classifier: Topic :: System :: Networking
Requires-Python: >=3.8
License-File: LICENSE
Requires-Dist: requests>=2.31.0
Requires-Dist: aiohttp>=3.9.0
Requires-Dist: pydantic>=2.0.0
Requires-Dist: rich>=13.0.0
Requires-Dist: PyYAML>=6.0
Requires-Dist: click>=8.1.0
Requires-Dist: jinja2>=3.1.0
Requires-Dist: jsonpath-ng>=1.5.0
Provides-Extra: curllm
Requires-Dist: ollama; extra == "curllm"
Requires-Dist: playwright; extra == "curllm"
Requires-Dist: beautifulsoup4; extra == "curllm"
Requires-Dist: lxml; extra == "curllm"
Provides-Extra: kafka
Requires-Dist: kafka-python>=2.0.0; extra == "kafka"
Provides-Extra: rabbitmq
Requires-Dist: pika>=1.3.0; extra == "rabbitmq"
Provides-Extra: postgres
Requires-Dist: psycopg2-binary>=2.9.0; extra == "postgres"
Requires-Dist: sqlalchemy>=2.0.0; extra == "postgres"
Provides-Extra: multimedia
Requires-Dist: opencv-python>=4.8.0; extra == "multimedia"
Requires-Dist: av>=10.0.0; extra == "multimedia"
Requires-Dist: numpy>=1.24.0; extra == "multimedia"
Provides-Extra: communication
Requires-Dist: python-telegram-bot>=20.0.0; extra == "communication"
Requires-Dist: twilio>=8.0.0; extra == "communication"
Requires-Dist: slack-sdk>=3.19.0; extra == "communication"
Requires-Dist: discord.py>=2.3.0; extra == "communication"
Requires-Dist: vonage>=3.3.0; extra == "communication"
Requires-Dist: plivo>=4.38.0; extra == "communication"
Provides-Extra: dev
Requires-Dist: pytest>=7.0.0; extra == "dev"
Requires-Dist: pytest-asyncio>=0.21.0; extra == "dev"
Requires-Dist: pytest-cov>=4.0.0; extra == "dev"
Requires-Dist: black>=23.0.0; extra == "dev"
Requires-Dist: flake8>=6.0.0; extra == "dev"
Requires-Dist: mypy>=1.0.0; extra == "dev"
Requires-Dist: pre-commit>=3.0.0; extra == "dev"
Provides-Extra: tracking
Requires-Dist: torch>=2.0.0; extra == "tracking"
Requires-Dist: torchvision>=0.15.0; extra == "tracking"
Provides-Extra: all
Requires-Dist: streamware[communication,curllm,dev,kafka,multimedia,postgres,rabbitmq,tracking]; extra == "all"
Dynamic: author
Dynamic: home-page
Dynamic: license-file
Dynamic: requires-python
